datacatalog_object_storage_processor/__init__.py
datacatalog_object_storage_processor/datacatalog_entity_factory.py
datacatalog_object_storage_processor/datacatalog_helper.py
datacatalog_object_storage_processor/datacatalog_object_storage_processor_cli.py
datacatalog_object_storage_processor/object_storage_processor.py
datacatalog_object_storage_processor/object_storage/__init__.py
datacatalog_object_storage_processor/object_storage/cloud_storage/__init__.py
datacatalog_object_storage_processor/object_storage/cloud_storage/storage_client_helper.py
datacatalog_object_storage_processor/object_storage/cloud_storage/storage_processor.py
datacatalog_object_storage_processor/utils/__init__.py
datacatalog_object_storage_processor/utils/values_comparable_object.py
datacatalog_object_storage_processor-0.1.2.dist-info/LICENSE
datacatalog_object_storage_processor-0.1.2.dist-info/METADATA
datacatalog_object_storage_processor-0.1.2.dist-info/WHEEL
datacatalog_object_storage_processor-0.1.2.dist-info/entry_points.txt
datacatalog_object_storage_processor-0.1.2.dist-info/top_level.txt
datacatalog_object_storage_processor-0.1.2.dist-info/RECORD
