Metadata-Version: 2.1
Name: datacatalog-object-storage-processor
Version: 0.1.2
Summary: A package for performing Data Catalog operations on object storage solutions
Home-page: https://github.com/mesmacosta/datacatalog-object-storage-processor
Author: Marcelo Costa
Author-email: mesmacosta@gmail.com
License: MIT license
Platform: Posix; MacOS X; Windows
Classifier: Development Status :: 3 - Alpha
Classifier: Natural Language :: English
Classifier: Programming Language :: Python
Classifier: Programming Language :: Python :: 3.6
Classifier: Programming Language :: Python :: 3.7
Requires-Python: >=3.6
Requires-Dist: google-cloud-datacatalog (<2,>=1)
Requires-Dist: google-cloud-storage
Requires-Dist: pandas
